<databaseChangeLog
  xmlns="http://www.liquibase.org/xml/ns/dbchangelog"
  xmlns:xsi="http://www.w3.org/2001/XMLSchema-instance"
  xsi:schemaLocation="http://www.liquibase.org/xml/ns/dbchangelog http://www.liquibase.org/xml/ns/dbchangelog/dbchangelog-3.1.xsd">
  <changeSet id="my-authority-01" author="mohsin.kerai">
    <createTable remarks="Table to Store Users Information for System Security"
      tableName="my_authority">
      <column autoIncrement="true" name="id" type="bigint">
        <constraints nullable="false" primaryKey="true" unique="true"/>
      </column>
      <column name="version" type="bigint" defaultValue="1"></column>
      <column name="name" type="varchar(255)">
        <constraints nullable="false" unique="true"/>
      </column>

      <!--AUDIT COLUMN-->
      <column defaultValueComputed="CURRENT_TIMESTAMP" name="created_on" type="datetime">
        <constraints nullable="false" unique="false"/>
      </column>
      <column defaultValueComputed="CURRENT_TIMESTAMP" name="updated_on" type="datetime">
        <constraints nullable="false" unique="false"/>
      </column>
      <column defaultValueComputed="null" name="created_by" type="varchar(255)">
        <constraints nullable="true" unique="false"/>
      </column>
      <column defaultValueComputed="null" name="updated_by" type="varchar(255)">
        <constraints nullable="true" unique="false"/>
      </column>
    </createTable>
  </changeSet>
  <changeSet id="my-authority-02" author="mohsin.kerai">
    <createIndex tableName="my_authority" indexName="users_username_index">
      <column name="name" />
    </createIndex>
  </changeSet>
  <changeSet id="my-authority-03" author="mohsin.kerai">
    <insert tableName="my_authority">
      <column name="id" value="1"/>
      <column name="name" value="ADMIN"/>
    </insert>
  </changeSet>
  <changeSet id="my-authority-04" author="mohsin.kerai">
    <insert tableName="my_authority">
      <column name="id" value="2"/>
      <column name="name" value="USER"/>
    </insert>
  </changeSet>
  <changeSet id="my-authority-05" author="mohsin.kerai">
    <insert tableName="my_authority">
      <column name="id" value="3"/>
      <column name="name" value="LEAD"/>
    </insert>
  </changeSet>
</databaseChangeLog>